Metadata-Version: 1.1
Name: imio.dms.policy
Version: 2.3.post1
Summary: DMS policy containing all packages required for dms to work
Home-page: http://svn.communesplone.org/svn/communesplone/imio.dms.policy
Author: IMIO
Author-email: support@imio.be
License: gpl
Keywords: Plone Python IMIO
Platform: UNKNOWN
Classifier: Programming Language :: Python
Classifier: Programming Language :: Python :: 2.7
